{"nodes": [{"id": "d_project_mmmmm_backend_src_controllers_machinecontroller_ts", "label": "machineController.ts", "file_type": "code", "source_file": "D:\\PROJECT\\mmmmm\\backend\\src\\controllers\\machineController.ts", "source_location": "L1"}, {"id": "machinecontroller_getmachines", "label": "getMachines()", "file_type": "code", "source_file": "D:\\PROJECT\\mmmmm\\backend\\src\\controllers\\machineController.ts", "source_location": "L4"}, {"id": "machinecontroller_getmachinebyid", "label": "getMachineById()", "file_type": "code", "source_file": "D:\\PROJECT\\mmmmm\\backend\\src\\controllers\\machineController.ts", "source_location": "L17"}, {"id": "machinecontroller_createmachine", "label": "createMachine()", "file_type": "code", "source_file": "D:\\PROJECT\\mmmmm\\backend\\src\\controllers\\machineController.ts", "source_location": "L43"}, {"id": "machinecontroller_updatemachine", "label": "updateMachine()", "file_type": "code", "source_file": "D:\\PROJECT\\mmmmm\\backend\\src\\controllers\\machineController.ts", "source_location": "L55"}, {"id": "machinecontroller_deletemachine", "label": "deleteMachine()", "file_type": "code", "source_file": "D:\\PROJECT\\mmmmm\\backend\\src\\controllers\\machineController.ts", "source_location": "L69"}, {"id": "machinecontroller_assignsettomachine", "label": "assignSetToMachine()", "file_type": "code", "source_file": "D:\\PROJECT\\mmmmm\\backend\\src\\controllers\\machineController.ts", "source_location": "L81"}], "edges": [{"source": "d_project_mmmmm_backend_src_controllers_machinecontroller_ts", "target": "express", "relation": "imports_from", "confidence": "EXTRACTED", "source_file": "D:\\PROJECT\\mmmmm\\backend\\src\\controllers\\machineController.ts", "source_location": "L1", "weight": 1.0}, {"source": "d_project_mmmmm_backend_src_controllers_machinecontroller_ts", "target": "d_project_mmmmm_backend_src_lib_prisma", "relation": "imports_from", "confidence": "EXTRACTED", "source_file": "D:\\PROJECT\\mmmmm\\backend\\src\\controllers\\machineController.ts", "source_location": "L2", "weight": 1.0}, {"source": "d_project_mmmmm_backend_src_controllers_machinecontroller_ts", "target": "machinecontroller_getmachines", "relation": "contains", "confidence": "EXTRACTED", "source_file": "D:\\PROJECT\\mmmmm\\backend\\src\\controllers\\machineController.ts", "source_location": "L4", "weight": 1.0}, {"source": "d_project_mmmmm_backend_src_controllers_machinecontroller_ts", "target": "machinecontroller_getmachinebyid", "relation": "contains", "confidence": "EXTRACTED", "source_file": "D:\\PROJECT\\mmmmm\\backend\\src\\controllers\\machineController.ts", "source_location": "L17", "weight": 1.0}, {"source": "d_project_mmmmm_backend_src_controllers_machinecontroller_ts", "target": "machinecontroller_createmachine", "relation": "contains", "confidence": "EXTRACTED", "source_file": "D:\\PROJECT\\mmmmm\\backend\\src\\controllers\\machineController.ts", "source_location": "L43", "weight": 1.0}, {"source": "d_project_mmmmm_backend_src_controllers_machinecontroller_ts", "target": "machinecontroller_updatemachine", "relation": "contains", "confidence": "EXTRACTED", "source_file": "D:\\PROJECT\\mmmmm\\backend\\src\\controllers\\machineController.ts", "source_location": "L55", "weight": 1.0}, {"source": "d_project_mmmmm_backend_src_controllers_machinecontroller_ts", "target": "machinecontroller_deletemachine", "relation": "contains", "confidence": "EXTRACTED", "source_file": "D:\\PROJECT\\mmmmm\\backend\\src\\controllers\\machineController.ts", "source_location": "L69", "weight": 1.0}, {"source": "d_project_mmmmm_backend_src_controllers_machinecontroller_ts", "target": "machinecontroller_assignsettomachine", "relation": "contains", "confidence": "EXTRACTED", "source_file": "D:\\PROJECT\\mmmmm\\backend\\src\\controllers\\machineController.ts", "source_location": "L81", "weight": 1.0}], "raw_calls": [{"caller_nid": "machinecontroller_getmachines", "callee": "findMany", "source_file": "D:\\PROJECT\\mmmmm\\backend\\src\\controllers\\machineController.ts", "source_location": "L6"}, {"caller_nid": "machinecontroller_getmachines", "callee": "json", "source_file": "D:\\PROJECT\\mmmmm\\backend\\src\\controllers\\machineController.ts", "source_location": "L11"}, {"caller_nid": "machinecontroller_getmachines", "callee": "next", "source_file": "D:\\PROJECT\\mmmmm\\backend\\src\\controllers\\machineController.ts", "source_location": "L13"}, {"caller_nid": "machinecontroller_getmachinebyid", "callee": "findUnique", "source_file": "D:\\PROJECT\\mmmmm\\backend\\src\\controllers\\machineController.ts", "source_location": "L20"}, {"caller_nid": "machinecontroller_getmachinebyid", "callee": "json", "source_file": "D:\\PROJECT\\mmmmm\\backend\\src\\controllers\\machineController.ts", "source_location": "L35"}, {"caller_nid": "machinecontroller_getmachinebyid", "callee": "status", "source_file": "D:\\PROJECT\\mmmmm\\backend\\src\\controllers\\machineController.ts", "source_location": "L35"}, {"caller_nid": "machinecontroller_getmachinebyid", "callee": "json", "source_file": "D:\\PROJECT\\mmmmm\\backend\\src\\controllers\\machineController.ts", "source_location": "L37"}, {"caller_nid": "machinecontroller_getmachinebyid", "callee": "next", "source_file": "D:\\PROJECT\\mmmmm\\backend\\src\\controllers\\machineController.ts", "source_location": "L39"}, {"caller_nid": "machinecontroller_createmachine", "callee": "create", "source_file": "D:\\PROJECT\\mmmmm\\backend\\src\\controllers\\machineController.ts", "source_location": "L46"}, {"caller_nid": "machinecontroller_createmachine", "callee": "json", "source_file": "D:\\PROJECT\\mmmmm\\backend\\src\\controllers\\machineController.ts", "source_location": "L49"}, {"caller_nid": "machinecontroller_createmachine", "callee": "status", "source_file": "D:\\PROJECT\\mmmmm\\backend\\src\\controllers\\machineController.ts", "source_location": "L49"}, {"caller_nid": "machinecontroller_createmachine", "callee": "next", "source_file": "D:\\PROJECT\\mmmmm\\backend\\src\\controllers\\machineController.ts", "source_location": "L51"}, {"caller_nid": "machinecontroller_updatemachine", "callee": "update", "source_file": "D:\\PROJECT\\mmmmm\\backend\\src\\controllers\\machineController.ts", "source_location": "L59"}, {"caller_nid": "machinecontroller_updatemachine", "callee": "json", "source_file": "D:\\PROJECT\\mmmmm\\backend\\src\\controllers\\machineController.ts", "source_location": "L63"}, {"caller_nid": "machinecontroller_updatemachine", "callee": "next", "source_file": "D:\\PROJECT\\mmmmm\\backend\\src\\controllers\\machineController.ts", "source_location": "L65"}, {"caller_nid": "machinecontroller_deletemachine", "callee": "delete", "source_file": "D:\\PROJECT\\mmmmm\\backend\\src\\controllers\\machineController.ts", "source_location": "L72"}, {"caller_nid": "machinecontroller_deletemachine", "callee": "send", "source_file": "D:\\PROJECT\\mmmmm\\backend\\src\\controllers\\machineController.ts", "source_location": "L75"}, {"caller_nid": "machinecontroller_deletemachine", "callee": "status", "source_file": "D:\\PROJECT\\mmmmm\\backend\\src\\controllers\\machineController.ts", "source_location": "L75"}, {"caller_nid": "machinecontroller_deletemachine", "callee": "next", "source_file": "D:\\PROJECT\\mmmmm\\backend\\src\\controllers\\machineController.ts", "source_location": "L77"}, {"caller_nid": "machinecontroller_assignsettomachine", "callee": "update", "source_file": "D:\\PROJECT\\mmmmm\\backend\\src\\controllers\\machineController.ts", "source_location": "L84"}, {"caller_nid": "machinecontroller_assignsettomachine", "callee": "json", "source_file": "D:\\PROJECT\\mmmmm\\backend\\src\\controllers\\machineController.ts", "source_location": "L93"}, {"caller_nid": "machinecontroller_assignsettomachine", "callee": "next", "source_file": "D:\\PROJECT\\mmmmm\\backend\\src\\controllers\\machineController.ts", "source_location": "L95"}]}